curlite/LICENSE
curlite/__init__.py
curlite/exceptions.py
curlite/lib.py
curlite-0.1.8.1.dist-info/METADATA
curlite-0.1.8.1.dist-info/WHEEL
curlite-0.1.8.1.dist-info/RECORD
