Metadata-Version: 2.1
Name: curlite
Version: 0.1.8.1
Summary: Python wrapper for libcurl to make http requests in a more pythonic way
Author: mohammed-workfellow
Author-email: mohammed@workfellow.ai
Requires-Python: >=3.9,<4.0
Classifier: Programming Language :: Python :: 3
Classifier: Programming Language :: Python :: 3.9
Classifier: Programming Language :: Python :: 3.10
Classifier: Programming Language :: Python :: 3.11
